{
  "suggestions": [
    {
      "suggestion_key": {
        "suggestion": "Shopping"
      },
      "children": [
        {
          "suggestion_key": {
            "suggestion": "Groceries"
          },
          "children": [
            {
              "suggestion_key": {
                "suggestion": "Milk"
              }
            },
            {
              "suggestion_key": {
                "suggestion": "Rice"
              }
            }
          ]
        },
        {
          "suggestion_key": {
            "suggestion": "vegetables"
          }
        }
      ]
    },
    {
      "suggestion_key": {
        "suggestion": "Office"
      },
      "children": [
        {
          "suggestion_key": {
            "suggestion": "A4 Paper"
          }
        },
        {
          "suggestion_key": {
            "suggestion": "Binds"
          }
        }
      ]
    }
  ]
}
